ratelimit/__init__.py
ratelimit/decorators.py
ratelimit/exception.py
ratelimit/types.py
ratelimit/utils.py
tests/__init__.py
tests/unit/__init__.py
tests/unit/decorator_test.py
ratelimit_extended-1.0.5.dist-info/LICENSE.txt
ratelimit_extended-1.0.5.dist-info/METADATA
ratelimit_extended-1.0.5.dist-info/WHEEL
ratelimit_extended-1.0.5.dist-info/top_level.txt
ratelimit_extended-1.0.5.dist-info/RECORD
