Metadata-Version: 2.1
Name: ratelimit-extended
Version: 1.0.5
Summary: API rate limit decorator
Home-page: https://github.com/omert11/ratelimit
Author: Ömer Faruk Yığın
Author-email: omert1122@gmail.com
License: MIT
Keywords: ratelimit,api,decorator
Classifier: Development Status :: 5 - Production/Stable
Classifier: Intended Audience :: Developers
Classifier: License :: OSI Approved :: MIT License
Classifier: Natural Language :: English
Classifier: Programming Language :: Python
Classifier: Topic :: Software Development
License-File: LICENSE.txt
